pycalco/__init__.py
pycalco/calculator.py
pycalco/shell.py
pycalco/aux/__init__.py
pycalco/aux/checkers.py
pycalco/aux/envs.py
pycalco/cmd/__init__.py
pycalco/cmd/calco.py
pycalco/cmd/pyeval.py
pycalco/cmd/symcalco.py
pycalco-0.9.2.dist-info/LICENSE
pycalco-0.9.2.dist-info/METADATA
pycalco-0.9.2.dist-info/WHEEL
pycalco-0.9.2.dist-info/entry_points.txt
pycalco-0.9.2.dist-info/top_level.txt
pycalco-0.9.2.dist-info/RECORD
