Metadata-Version: 2.1
Name: pycalco
Version: 0.9.2
Summary: A powerful arithmetic and symbolic expressions evaluator
Home-page: https://github.com/trabdlkarim/pycalco
Author: Toure A. Karim
Author-email: contact@trabdlkarim.com
License: UNKNOWN
Project-URL: Homepage, https://gh.trabdlkarim.com/pycalco
Project-URL: Documentation, https://docs.trabdlkarim.com/projects/pycalco/en/latest
Project-URL: Bug Reports, https://github.com/trabdlkarim/pycalco/issues
Project-URL: Source Code, https://github.com/trabdlkarim/pycalco/
Project-URL: Say Thanks!, https://saythanks.io/to/trabdlkarim%40programmer.net
Keywords: pycalco,calculator,calc,calco,arithmetics,expression,maths
Platform: UNKNOWN
Classifier: Development Status :: 5 - Production/Stable
Classifier: Intended Audience :: End Users/Desktop
Classifier: Topic :: Utilities
Classifier: License :: OSI Approved :: BSD License
Classifier: Programming Language :: Python :: 3
Classifier: Programming Language :: Python :: 3.5
Classifier: Programming Language :: Python :: 3.6
Classifier: Programming Language :: Python :: 3.7
Classifier: Programming Language :: Python :: 3.8
Classifier: Programming Language :: Python :: 3 :: Only
Classifier: Programming Language :: Python :: Implementation :: CPython
Classifier: Operating System :: OS Independent
Requires-Python: >=3.4
Requires-Dist: click
Requires-Dist: sympy
Provides-Extra: dev
Requires-Dist: check-manifest ; extra == 'dev'
Provides-Extra: test
Requires-Dist: coverage ; extra == 'test'
